pyFilo/__init__.py
pyFilo/__main__.py
pyFilo/blast.py
pyFilo/fasta.py
pyFilo/version.py
pyFilo-0.0.1.dist-info/METADATA
pyFilo-0.0.1.dist-info/WHEEL
pyFilo-0.0.1.dist-info/entry_points.txt
pyFilo-0.0.1.dist-info/top_level.txt
pyFilo-0.0.1.dist-info/RECORD
